{
    "crs": {
        "properties": {
            "name": "urn:ogc:def:crs:EPSG::3857"
        },
        "type": "name"
    },
    "features": [
        {
            "geometry": {
                "coordinates": [
                    1.2680540084838867,
                    0.9709510207176208
                ],
                "type": "Point"
            },
            "properties": {
                "frame": "map",
                "id": 1
            },
            "type": "Feature"
        },
        {
            "geometry": {
                "coordinates": [
                    1.4821540117263794,
                    0.6311569809913635
                ],
                "type": "Point"
            },
            "properties": {
                "frame": "map",
                "id": 2
            },
            "type": "Feature"
        },
        {
            "geometry": {
                "coordinates": [
                    1.7847520112991333,
                    -0.004364000167697668
                ],
                "type": "Point"
            },
            "properties": {
                "frame": "map",
                "id": 3
            },
            "type": "Feature"
        },
        {
            "geometry": {
                "coordinates": [
                    -0.045997001230716705,
                    -0.028175000101327896
                ],
                "type": "Point"
            },
            "properties": {
                "frame": "map",
                "id": 5
            },
            "type": "Feature"
        },
        {
            "geometry": {
                "coordinates": [
                    0.5273640155792236,
                    0.5429109930992126
                ],
                "type": "Point"
            },
            "properties": {
                "frame": "map",
                "id": 6
            },
            "type": "Feature"
        },
        {
            "geometry": {
                "type": "MultiLineString"
            },
            "properties": {
                "cost": 0.0,
                "endid": 2,
                "id": 4,
                "overridable": true,
                "startid": 1
            },
            "type": "Feature"
        },
        {
            "geometry": {
                "type": "MultiLineString"
            },
            "properties": {
                "cost": 0.0,
                "endid": 3,
                "id": 9,
                "overridable": true,
                "startid": 2
            },
            "type": "Feature"
        },
        {
            "geometry": {
                "type": "MultiLineString"
            },
            "properties": {
                "cost": 0.0,
                "endid": 6,
                "id": 7,
                "overridable": true,
                "startid": 5
            },
            "type": "Feature"
        },
        {
            "geometry": {
                "type": "MultiLineString"
            },
            "properties": {
                "cost": 0.0,
                "endid": 1,
                "id": 8,
                "overridable": true,
                "startid": 6
            },
            "type": "Feature"
        }
    ],
    "name": "graph",
    "type": "FeatureCollection"
}
